testcases_writer_ai_tool/__init__.py
testcases_writer_ai_tool/generate_test_cases.py
testcases_writer_ai_tool-0.1.0.dist-info/METADATA
testcases_writer_ai_tool-0.1.0.dist-info/WHEEL
testcases_writer_ai_tool-0.1.0.dist-info/entry_points.txt
testcases_writer_ai_tool-0.1.0.dist-info/top_level.txt
testcases_writer_ai_tool-0.1.0.dist-info/RECORD
