Metadata-Version: 2.4
Name: testcases-writer-ai-tool
Version: 0.1.0
Summary: Automatically generate pytest test cases for your Python app using Claude AI.
Home-page: https://github.com/yourusername/testcases-writer-ai-tool
Author: Your Name
Author-email: your.email@example.com
License: MIT
Classifier: Programming Language :: Python :: 3
Classifier: License :: OSI Approved :: MIT License
Classifier: Operating System :: OS Independent
Requires-Python: >=3.7
Requires-Dist: requests
Requires-Dist: pytest
Dynamic: author
Dynamic: author-email
Dynamic: classifier
Dynamic: description
Dynamic: description-content-type
Dynamic: home-page
Dynamic: license
Dynamic: requires-dist
Dynamic: requires-python
Dynamic: summary
